[{"id": "1", "title": "Summoning Ancient Heroes", "type": "Manga Canon", "date": "2011-10-01", "class": "green"}, {"id": "2", "title": "False Start", "type": "Manga Canon", "date": "2011-10-08", "class": "green"}, {"id": "3", "title": "Land of Fuyuki", "type": "Manga Canon", "date": "2011-10-15", "class": "green"}, {"id": "4", "title": "Blade of the Demonic Spear", "type": "Manga Canon", "date": "2011-10-22", "class": "green"}, {"id": "5", "title": "The Vicious Beast Roars", "type": "Manga Canon", "date": "2011-10-29", "class": "green"}, {"id": "6", "title": "Night of Schemes", "type": "Manga Canon", "date": "2011-11-05", "class": "green"}, {"id": "7", "title": "The Evil Forest", "type": "Manga Canon", "date": "2011-11-12", "class": "green"}, {"id": "8", "title": "The Magus Killer", "type": "Manga Canon", "date": "2011-11-19", "class": "green"}, {"id": "9", "title": "Master and Servant", "type": "Manga Canon", "date": "2011-11-26", "class": "green"}, {"id": "10", "title": "Rin's Adventure", "type": "Mixed Canon/Filler", "date": "2011-12-03", "class": "green"}, {"id": "11", "title": "The Grail Dialogue", "type": "Manga Canon", "date": "2011-12-10", "class": "green"}, {"id": "12", "title": "The Grail's Invitation", "type": "Manga Canon", "date": "2011-12-17", "class": "green"}, {"id": "13", "title": "Forbidden Banquet", "type": "Manga Canon", "date": "2011-12-24", "class": "green"}, {"id": "14", "title": "The Bloody Battle of Mion River", "type": "Manga Canon", "date": "2012-04-07", "class": "green"}, {"id": "15", "title": "Golden Radiance", "type": "Manga Canon", "date": "2012-04-14", "class": "green"}, {"id": "16", "title": "The Terminus of Honor", "type": "Manga Canon", "date": "2012-04-21", "class": "green"}, {"id": "17", "title": "The Eighth Contract", "type": "Manga Canon", "date": "2012-04-28", "class": "green"}, {"id": "18", "title": "Distant Memories", "type": "Mixed Canon/Filler", "date": "2012-05-05", "class": "green"}, {"id": "19", "title": "Where Justice is Found", "type": "Mixed Canon/Filler", "date": "2012-05-12", "class": "green"}, {"id": "20", "title": "Return of the Assassin", "type": "Manga Canon", "date": "2012-05-19", "class": "green"}, {"id": "21", "title": "Knight on Two Wheels", "type": "Manga Canon", "date": "2012-05-26", "class": "green"}, {"id": "22", "title": "All the World's Evils", "type": "Manga Canon", "date": "2012-06-02", "class": "green"}, {"id": "23", "title": "The Sea at the End of the World", "type": "Manga Canon", "date": "2012-06-09", "class": "green"}, {"id": "24", "title": "The Last Command Spell", "type": "Manga Canon", "date": "2012-06-16", "class": "green"}, {"id": "25", "title": "Fate/Zero", "type": "Manga Canon", "date": "2012-06-23", "class": "green"}]