[{"id": "1", "title": "Dio the Invader", "type": "Manga Canon", "date": "2012-10-05", "class": "green"}, {"id": "2", "title": "A Letter from the Past", "type": "Manga Canon", "date": "2012-10-12", "class": "green"}, {"id": "3", "title": "Youth With Dio", "type": "Manga Canon", "date": "2012-10-19", "class": "green"}, {"id": "4", "title": "Overdrive", "type": "Manga Canon", "date": "2012-10-26", "class": "green"}, {"id": "5", "title": "The Dark Knights", "type": "Manga Canon", "date": "2012-11-02", "class": "green"}, {"id": "6", "title": "Tomorrow's Courage", "type": "Manga Canon", "date": "2012-11-09", "class": "green"}, {"id": "7", "title": "Sorrowful Successor", "type": "Manga Canon", "date": "2012-11-16", "class": "green"}, {"id": "8", "title": "Bloody Battle! JoJo and Dio", "type": "Manga Canon", "date": "2012-11-23", "class": "green"}, {"id": "9", "title": "The Final Ripple!", "type": "Manga Canon", "date": "2012-11-30", "class": "green"}, {"id": "10", "title": "New York's JoJo", "type": "Manga Canon", "date": "2012-12-07", "class": "green"}, {"id": "11", "title": "The Game Master", "type": "Manga Canon", "date": "2012-12-14", "class": "green"}, {"id": "12", "title": "The Pillar Man", "type": "Manga Canon", "date": "2012-12-21", "class": "green"}, {"id": "13", "title": "JoJo vs. The Ultimate Lifeform", "type": "Manga Canon", "date": "2013-01-04", "class": "green"}, {"id": "14", "title": "Ultimate Warriors from Ancient Times", "type": "Manga Canon", "date": "2013-01-11", "class": "green"}, {"id": "15", "title": "A Hero's Proof", "type": "Manga Canon", "date": "2013-01-18", "class": "green"}, {"id": "16", "title": "Lisa Lisa, Hamon Coach", "type": "Manga Canon", "date": "2013-01-25", "class": "green"}, {"id": "17", "title": "The Deeper Plan", "type": "Manga Canon", "date": "2013-02-01", "class": "green"}, {"id": "18", "title": "Von Stroheim's Revenge", "type": "Manga Canon", "date": "2013-02-08", "class": "green"}, {"id": "19", "title": "A Race Toward the Brink", "type": "Manga Canon", "date": "2013-02-15", "class": "green"}, {"id": "20", "title": "Young Caesar", "type": "Manga Canon", "date": "2013-02-22", "class": "green"}, {"id": "21", "title": "A Hundred Against Two", "type": "Manga Canon", "date": "2013-03-01", "class": "green"}, {"id": "22", "title": "A True Warrior", "type": "Manga Canon", "date": "2013-03-08", "class": "green"}, {"id": "23", "title": "The Warrior of Wind", "type": "Manga Canon", "date": "2013-03-15", "class": "green"}, {"id": "24", "title": "The Ties that Bind JoJo", "type": "Manga Canon", "date": "2013-03-22", "class": "green"}, {"id": "25", "title": "The Birth of a Superbeing", "type": "Manga Canon", "date": "2013-03-29", "class": "green"}, {"id": "26", "title": "The Ascendant One", "type": "Manga Canon", "date": "2013-04-05", "class": "green"}, {"id": "27", "title": "The Man Possessed by an Evil Spirit", "type": "Manga Canon", "date": "2014-04-04", "class": "green"}, {"id": "28", "title": "Who Will Be the Judge!?", "type": "Manga Canon", "date": "2014-04-11", "class": "green"}, {"id": "29", "title": "The Curse of DIO", "type": "Manga Canon", "date": "2014-04-18", "class": "green"}, {"id": "30", "title": "Tower of Gray", "type": "Manga Canon", "date": "2014-04-25", "class": "green"}, {"id": "31", "title": "Silver Chariot", "type": "Manga Canon", "date": "2014-05-02", "class": "green"}, {"id": "32", "title": "Dark Blue Moon", "type": "Manga Canon", "date": "2014-05-09", "class": "green"}, {"id": "33", "title": "Strength", "type": "Manga Canon", "date": "2014-05-16", "class": "green"}, {"id": "34", "title": "The Devil", "type": "Manga Canon", "date": "2014-05-23", "class": "green"}, {"id": "35", "title": "Yellow Temperance", "type": "Manga Canon", "date": "2014-06-30", "class": "green"}, {"id": "36", "title": "The Emperor and The Hanged Man, Part 1", "type": "Manga Canon", "date": "2014-06-06", "class": "green"}, {"id": "37", "title": "The Emperor and The Hanged Man, Part 2", "type": "Manga Canon", "date": "2014-06-13", "class": "green"}, {"id": "38", "title": "The Empress", "type": "Manga Canon", "date": "2014-06-20", "class": "green"}, {"id": "39", "title": "Wheel of Fortune", "type": "Manga Canon", "date": "2014-06-27", "class": "green"}, {"id": "40", "title": "Justice, Part 1", "type": "Manga Canon", "date": "2014-07-04", "class": "green"}, {"id": "41", "title": "Justice, Part 2", "type": "Manga Canon", "date": "2014-07-11", "class": "green"}, {"id": "42", "title": "The Lovers, Part 1", "type": "Manga Canon", "date": "2014-07-18", "class": "green"}, {"id": "43", "title": "The Lovers, Part 2", "type": "Manga Canon", "date": "2014-07-25", "class": "green"}, {"id": "44", "title": "The Sun", "type": "Manga Canon", "date": "2014-08-01", "class": "green"}, {"id": "45", "title": "Death 13, Part 1", "type": "Manga Canon", "date": "2014-08-28", "class": "green"}, {"id": "46", "title": "Death 13, Part 2", "type": "Manga Canon", "date": "2014-08-15", "class": "green"}, {"id": "47", "title": "Judgment, Part 1", "type": "Manga Canon", "date": "2014-08-22", "class": "green"}, {"id": "48", "title": "Judgment, Part 2", "type": "Manga Canon", "date": "2014-08-29", "class": "green"}, {"id": "49", "title": "The High Priestess, Part 1", "type": "Manga Canon", "date": "2014-09-05", "class": "green"}, {"id": "50", "title": "The High Priestess, Part 2", "type": "Manga Canon", "date": "2014-09-12", "class": "green"}, {"id": "51", "title": "Iggy the Fool and Geb's N'doul, Part 1", "type": "Manga Canon", "date": "2015-01-09", "class": "green"}, {"id": "52", "title": "Iggy the Fool and Geb's N'doul, Part 2", "type": "Manga Canon", "date": "2015-01-16", "class": "green"}, {"id": "53", "title": "Khnum's Zenyatta and Thoth's Mondatta", "type": "Manga Canon", "date": "2015-01-23", "class": "green"}, {"id": "54", "title": "Anubis, Part 1", "type": "Manga Canon", "date": "2015-01-30", "class": "green"}, {"id": "55", "title": "Anubis, Part 2", "type": "Manga Canon", "date": "2015-02-06", "class": "green"}, {"id": "56", "title": "Bast's Mariah, Part 1", "type": "Manga Canon", "date": "2015-02-13", "class": "green"}, {"id": "57", "title": "Bast's Mariah, Part 2", "type": "Manga Canon", "date": "2015-02-20", "class": "green"}, {"id": "58", "title": "Set's Alessi, Part 1", "type": "Manga Canon", "date": "2015-02-27", "class": "green"}, {"id": "59", "title": "Set's Alessi, Part 2", "type": "Manga Canon", "date": "2015-03-06", "class": "green"}, {"id": "60", "title": "D'Arby the Gambler, Part 1", "type": "Manga Canon", "date": "2015-03-13", "class": "green"}, {"id": "61", "title": "D'Arby the Gambler, Part 2", "type": "Manga Canon", "date": "2015-03-20", "class": "green"}, {"id": "62", "title": "Hol Horse and Mondatta, Part 1", "type": "Manga Canon", "date": "2015-03-27", "class": "green"}, {"id": "63", "title": "Hol Horse and Mondatta, Part 2", "type": "Manga Canon", "date": "2015-04-03", "class": "green"}, {"id": "64", "title": "The Guardian of Hell, Pet Shop, Part 1", "type": "Manga Canon", "date": "2015-04-10", "class": "green"}, {"id": "65", "title": "The Guardian of Hell, Pet Shop, Part 2", "type": "Manga Canon", "date": "2015-04-17", "class": "green"}, {"id": "66", "title": "D'Arby the Player, Part 1", "type": "Manga Canon", "date": "2015-04-24", "class": "green"}, {"id": "67", "title": "D'Arby the Player, Part 2", "type": "Manga Canon", "date": "2015-05-01", "class": "green"}, {"id": "68", "title": "The Miasma of the Void, Cool Ice, Part 1", "type": "Manga Canon", "date": "2015-05-08", "class": "green"}, {"id": "69", "title": "The Miasma of the Void, Cool Ice, Part 2", "type": "Manga Canon", "date": "2015-05-15", "class": "green"}, {"id": "70", "title": "The Miasma of the Void, Cool Ice, Part 3", "type": "Manga Canon", "date": "2015-05-22", "class": "green"}, {"id": "71", "title": "DIO's World, Part 1", "type": "Manga Canon", "date": "2015-05-29", "class": "green"}, {"id": "72", "title": "DIO's World, Part 2", "type": "Manga Canon", "date": "2015-06-05", "class": "green"}, {"id": "73", "title": "DIO's World, Part 3", "type": "Manga Canon", "date": "2015-06-12", "class": "green"}, {"id": "74", "title": "Long Journey Farewell, My Friends", "type": "Manga Canon", "date": "2015-06-19", "class": "green"}, {"id": "75", "title": "Jotaro Kujo! Meets Josuke Higashikata", "type": "Manga Canon", "date": "2016-04-01", "class": "green"}, {"id": "76", "title": "Josuke Higashikata! Meets Angelo", "type": "Manga Canon", "date": "2016-04-08", "class": "green"}, {"id": "77", "title": "The Nijimura Brothers, Part 1", "type": "Manga Canon", "date": "2016-04-15", "class": "green"}, {"id": "78", "title": "The Nijimura Brothers, Part 2", "type": "Manga Canon", "date": "2016-04-22", "class": "green"}, {"id": "79", "title": "The Nijimura Brothers, Part 3", "type": "Manga Canon", "date": "2016-04-29", "class": "green"}, {"id": "80", "title": "Koichi Hirose (Reverb)", "type": "Manga Canon", "date": "2016-05-06", "class": "green"}, {"id": "81", "title": "Toshikazu Hazamada (Show Off)", "type": "Manga Canon", "date": "2016-05-13", "class": "green"}, {"id": "82", "title": "Yukako Yamagishi Falls in Love, Part 1", "type": "Manga Canon", "date": "2016-05-20", "class": "green"}, {"id": "83", "title": "Yukako Yamagishi Falls in Love, Part 2", "type": "Manga Canon", "date": "2016-05-27", "class": "green"}, {"id": "84", "title": "Let's Go Eat Some Italian Food", "type": "Manga Canon", "date": "2016-06-03", "class": "green"}, {"id": "85", "title": "Chili Pepper, Part 1", "type": "Manga Canon", "date": "2016-06-10", "class": "green"}, {"id": "86", "title": "Chili Pepper, Part 2", "type": "Manga Canon", "date": "2016-06-17", "class": "green"}, {"id": "87", "title": "We Picked Up Something Crazy!", "type": "Manga Canon", "date": "2016-06-24", "class": "green"}, {"id": "88", "title": "Let's Go to the Manga Artist's House, Part 1", "type": "Manga Canon", "date": "2016-07-01", "class": "green"}, {"id": "89", "title": "Let's Go to the Manga Artist's House, Part 2", "type": "Manga Canon", "date": "2016-07-08", "class": "green"}, {"id": "90", "title": "Let's Go Hunting!", "type": "Manga Canon", "date": "2016-07-15", "class": "green"}, {"id": "91", "title": "Rohan Kishibe's Adventure", "type": "Manga Canon", "date": "2016-07-22", "class": "green"}, {"id": "92", "title": "Shigechi's Harvest, Part 1", "type": "Manga Canon", "date": "2016-07-29", "class": "green"}, {"id": "93", "title": "Shigechi's Harvest, Part 2", "type": "Manga Canon", "date": "2016-08-05", "class": "green"}, {"id": "94", "title": "Yukako Yamagishi Dreams of Cinderella", "type": "Manga Canon", "date": "2016-08-12", "class": "green"}, {"id": "95", "title": "Yoshikage Kira Just Wants to Live Quietly, Part 1", "type": "Manga Canon", "date": "2016-08-19", "class": "green"}, {"id": "96", "title": "Yoshikage Kira Just Wants to Live Quietly, Part 2", "type": "Manga Canon", "date": "2016-08-26", "class": "green"}, {"id": "97", "title": "Heart Attack, Part 1", "type": "Manga Canon", "date": "2016-09-02", "class": "green"}, {"id": "98", "title": "Heart Attack, Part 2", "type": "Manga Canon", "date": "2016-09-09", "class": "green"}, {"id": "99", "title": "Heart Father", "type": "Manga Canon", "date": "2016-09-16", "class": "green"}, {"id": "100", "title": "Rosham Boy is Here!", "type": "Manga Canon", "date": "2016-09-23", "class": "green"}, {"id": "101", "title": "I'm an Alien", "type": "Manga Canon", "date": "2016-09-30", "class": "green"}, {"id": "102", "title": "Highway Go Go, Part 1", "type": "Manga Canon", "date": "2016-10-07", "class": "green"}, {"id": "103", "title": "Highway Go Go, Part 2", "type": "Manga Canon", "date": "2016-10-14", "class": "green"}, {"id": "104", "title": "Cats Love Yoshikage Kira", "type": "Manga Canon", "date": "2016-10-21", "class": "green"}, {"id": "105", "title": "July 15th (Thurs), Part 1", "type": "Manga Canon", "date": "2016-10-28", "class": "green"}, {"id": "106", "title": "July 15th (Thurs), Part 2", "type": "Manga Canon", "date": "2016-11-04", "class": "green"}, {"id": "107", "title": "July 15th (Thurs), Part 3", "type": "Manga Canon", "date": "2016-11-11", "class": "green"}, {"id": "108", "title": "July 15th (Thurs), Part 4", "type": "Manga Canon", "date": "2016-11-18", "class": "green"}, {"id": "109", "title": "Bites the Dust, Part 1", "type": "Manga Canon", "date": "2016-11-25", "class": "green"}, {"id": "110", "title": "Bites the Dust, Part 2", "type": "Manga Canon", "date": "2016-12-02", "class": "green"}, {"id": "111", "title": "Shining D (Diamond) is Unbreakable, Part 1", "type": "Manga Canon", "date": "2016-12-09", "class": "green"}, {"id": "112", "title": "Shining D (Diamond) is Unbreakable, Part 2", "type": "Manga Canon", "date": "2016-12-16", "class": "green"}, {"id": "113", "title": "Goodbye, Morioh - The Heart of Gold", "type": "Manga Canon", "date": "2016-12-23", "class": "green"}, {"id": "114", "title": "Golden Wind", "type": "Manga Canon", "date": "2018-10-05", "class": "green"}, {"id": "115", "title": "Bucciarati Appears", "type": "Manga Canon", "date": "2018-10-12", "class": "green"}, {"id": "116", "title": "Meet the Mafioso Behind the Wall", "type": "Manga Canon", "date": "2018-10-19", "class": "green"}, {"id": "117", "title": "Joining the Famiglia", "type": "Manga Canon", "date": "2018-10-26", "class": "green"}, {"id": "118", "title": "Find Polpo's Fortune!", "type": "Manga Canon", "date": "2018-11-02", "class": "green"}, {"id": "119", "title": "Moody Jazz's Counterattack", "type": "Manga Canon", "date": "2018-11-09", "class": "green"}, {"id": "120", "title": "Six Bullets Appears, Part 1", "type": "Manga Canon", "date": "2018-11-16", "class": "green"}, {"id": "121", "title": "Six Bullets Appears, Part 2", "type": "Manga Canon", "date": "2018-11-23", "class": "green"}, {"id": "122", "title": "The First Mission from the Boss", "type": "Manga Canon", "date": "2018-11-30", "class": "green"}, {"id": "123", "title": "Hitman Team", "type": "Manga Canon", "date": "2018-12-07", "class": "green"}, {"id": "124", "title": "Narancia's Li'l Bomber", "type": "Manga Canon", "date": "2018-12-14", "class": "green"}, {"id": "125", "title": "The Second Mission from the Boss", "type": "Manga Canon", "date": "2018-12-21", "class": "green"}, {"id": "126", "title": "Mirror Man and Purple Smoke", "type": "Manga Canon", "date": "2018-12-28", "class": "green"}, {"id": "127", "title": "Il Treno Espresso per Firenze", "type": "Manga Canon", "date": "2019-01-11", "class": "green"}, {"id": "128", "title": "Thankful Death, Part 1", "type": "Manga Canon", "date": "2019-01-18", "class": "green"}, {"id": "129", "title": "Thankful Death, Part 2", "type": "Manga Canon", "date": "2019-01-25", "class": "green"}, {"id": "130", "title": "Babyhead", "type": "Manga Canon", "date": "2019-02-01", "class": "green"}, {"id": "131", "title": "Verso Venezia!", "type": "Manga Canon", "date": "2019-02-08", "class": "green"}, {"id": "132", "title": "White Ice", "type": "Manga Canon", "date": "2019-02-15", "class": "green"}, {"id": "133", "title": "The Final Mission from the Boss", "type": "Manga Canon", "date": "2019-02-22", "class": "green"}, {"id": "134", "title": "The Mystery of Emperor Crimson", "type": "Manga Canon", "date": "2019-03-01", "class": "green"}, {"id": "135", "title": "The \"G\" in Gozzo", "type": "Manga Canon", "date": "2019-03-15", "class": "green"}, {"id": "136", "title": "Crush and Talking Mouth", "type": "Manga Canon", "date": "2019-03-22", "class": "green"}, {"id": "137", "title": "Notorious Chase", "type": "Manga Canon", "date": "2019-03-29", "class": "green"}, {"id": "138", "title": "Spicy Lady", "type": "Manga Canon", "date": "2019-04-05", "class": "green"}, {"id": "139", "title": "A Little Story from the Past - My Name is Doppio", "type": "Manga Canon", "date": "2019-04-12", "class": "green"}, {"id": "140", "title": "Emperor Crimson vs. Metallic", "type": "Manga Canon", "date": "2019-04-19", "class": "green"}, {"id": "141", "title": "Beneath a Sky on the Verge of Falling", "type": "Manga Canon", "date": "2019-04-26", "class": "green"}, {"id": "142", "title": "Verso il Colosseo di Roma", "type": "Manga Canon", "date": "2019-05-10", "class": "green"}, {"id": "143", "title": "Green Tea and Sanctuary, Part 1", "type": "Manga Canon", "date": "2019-05-17", "class": "green"}, {"id": "144", "title": "Green Tea and Sanctuary, Part 2", "type": "Manga Canon", "date": "2019-05-24", "class": "green"}, {"id": "145", "title": "Green Tea and Sanctuary, Part 3", "type": "Manga Canon", "date": "2019-05-31", "class": "green"}, {"id": "146", "title": "His Name is Diavolo", "type": "Manga Canon", "date": "2019-06-07", "class": "green"}, {"id": "147", "title": "The Requiem Quietly Plays, Part 1", "type": "Manga Canon", "date": "2019-06-14", "class": "green"}, {"id": "148", "title": "The Requiem Quietly Plays, Part 2", "type": "Manga Canon", "date": "2019-06-21", "class": "green"}, {"id": "149", "title": "Diavolo Surfaces", "type": "Manga Canon", "date": "2019-06-28", "class": "green"}, {"id": "150", "title": "King of Kings", "type": "Manga Canon", "date": "2019-07-05", "class": "green"}, {"id": "151", "title": "Golden Wind Requiem", "type": "Manga Canon", "date": "2019-07-28", "class": "green"}, {"id": "152", "title": "The Sleeping Slave", "type": "Manga Canon", "date": "2019-07-28", "class": "green"}]